tap/__init__.py
tap/py.typed
tap/tap.py
tap/tapify.py
tap/utils.py
typed_argument_parser-1.10.1.dist-info/LICENSE.txt
typed_argument_parser-1.10.1.dist-info/METADATA
typed_argument_parser-1.10.1.dist-info/WHEEL
typed_argument_parser-1.10.1.dist-info/top_level.txt
typed_argument_parser-1.10.1.dist-info/RECORD
