Metadata-Version: 2.1
Name: typed-argument-parser
Version: 1.10.1
Summary: Typed Argument Parser
Author-email: Jesse Michel <jessem.michel@gmail.com>, Kyle Swanson <swansonk.14@gmail.com>
Maintainer-email: Jesse Michel <jessem.michel@gmail.com>, Kyle Swanson <swansonk.14@gmail.com>
License: Copyright (c) 2022 Jesse Michel and Kyle Swanson
Project-URL: Homepage, https://github.com/swansonk14/typed-argument-parser
Project-URL: Issues, https://github.com/swansonk14/typed-argument-parser/issues
Keywords: typing,argument parser,python
Classifier: Programming Language :: Python :: 3
Classifier: Programming Language :: Python :: 3.8
Classifier: Programming Language :: Python :: 3.9
Classifier: Programming Language :: Python :: 3.10
Classifier: Programming Language :: Python :: 3.11
Classifier: Programming Language :: Python :: 3.12
Classifier: License :: OSI Approved :: MIT License
Classifier: Operating System :: OS Independent
Classifier: Typing :: Typed
Requires-Python: >=3.8
License-File: LICENSE.txt
Requires-Dist: docstring-parser >=0.15
Requires-Dist: packaging
Requires-Dist: typing-inspect >=0.7.1
Provides-Extra: dev
Requires-Dist: typed-argument-parser[dev-no-pydantic] ; extra == 'dev'
Requires-Dist: pydantic >=2.5.0 ; extra == 'dev'
Provides-Extra: dev-no-pydantic
Requires-Dist: pytest ; extra == 'dev-no-pydantic'
Requires-Dist: pytest-cov ; extra == 'dev-no-pydantic'
Requires-Dist: flake8 ; extra == 'dev-no-pydantic'
